fastzdp_sqlmodel/__init__.py
fastzdp_sqlmodel/add.py
fastzdp_sqlmodel/delete.py
fastzdp_sqlmodel/engine.py
fastzdp_sqlmodel/get.py
fastzdp_sqlmodel/get_analysis.py
fastzdp_sqlmodel/get_page.py
fastzdp_sqlmodel/is_bool.py
fastzdp_sqlmodel/table.py
fastzdp_sqlmodel/update.py
fastzdp_sqlmodel-0.1.5.dist-info/LICENSE
fastzdp_sqlmodel-0.1.5.dist-info/METADATA
fastzdp_sqlmodel-0.1.5.dist-info/WHEEL
fastzdp_sqlmodel-0.1.5.dist-info/RECORD
