Metadata-Version: 2.1
Name: fastzdp-sqlmodel
Version: 0.1.5
Summary: 基于SQLModel封装的专用于FastAPI处理MySQL数据库业务的框架
Author: zhangdapeng520
Author-email: 1156956636@qq.com
Requires-Python: >=3.7,<4.0
Classifier: Programming Language :: Python :: 3
Classifier: Programming Language :: Python :: 3.7
Classifier: Programming Language :: Python :: 3.8
Classifier: Programming Language :: Python :: 3.9
Classifier: Programming Language :: Python :: 3.10
Classifier: Programming Language :: Python :: 3.11
Classifier: Programming Language :: Python :: 3.12
Requires-Dist: cryptography (>=43.0.1,<44.0.0)
Requires-Dist: pymysql (>=1.1.1,<2.0.0)
Requires-Dist: sqlmodel (>=0.0.22,<0.0.23)
